.coveragerc
.flake8
.gitignore
.readthedocs.yaml
CHANGELOG.md
LICENSE
MANIFEST.in
Makefile.am
Makefile.in
NERSC_installation.md
README.md
aclocal.m4
ar-lib
compile
config.guess
config.h.in
config.sub
configure
configure.ac
depcomp
install-sh
ltmain.sh
missing
pyproject.toml
setup.py
.github/environment.yml
.github/workflows/ci.yml
doc/1BasicFunctionality.html
doc/1BasicFunctionality.ipynb
doc/2Spin.html
doc/2Spin.ipynb
doc/3Covariances.html
doc/3Covariances.ipynb
doc/4Catalogs.html
doc/4Catalogs.ipynb
doc/5AnisotropicWeighting.html
doc/5AnisotropicWeighting.ipynb
doc/6CatalogsDeprojection.html
doc/6CatalogsDeprojection.ipynb
doc/Makefile
doc/apidoc.sh
doc/conf.py
doc/doc_scientific.pdf
doc/doc_scientific.tex
doc/index.rst
doc/kSZ_tutorial.ipynb
doc/requirements.txt
doc/Paper/cls_cmb.pdf
doc/Paper/cls_cont_lss.pdf
doc/Paper/cls_lss.pdf
doc/Paper/main.bib
doc/Paper/main.tex
doc/Paper/maps_cmb.pdf
doc/Paper/maps_contamination.pdf
doc/Paper/maps_lss_flat.pdf
doc/Paper/maps_lss_sph.pdf
doc/Paper/mnrasb.bst
doc/Paper/mnrasb.cls
doc/Paper/time_scaling.pdf
doc/Paper/timing.pdf
doc/Paper/val_chi2_cmb_flat.pdf
doc/Paper/val_chi2_cmb_sph.pdf
doc/Paper/val_chi2_lss_flat.pdf
doc/Paper/val_chi2_lss_sph.pdf
doc/Paper/val_cl_cmb_flat.pdf
doc/Paper/val_cl_cmb_sph.pdf
doc/Paper/val_cl_lss_flat.pdf
doc/Paper/val_cl_lss_sph.pdf
doc/Paper/val_cl_lss_sph_4096.pdf
doc/Paper/val_cmb_bpw.pdf
doc/Paper/val_covar_cmb_sph.pdf
doc/Paper/val_covar_cmb_sph_nocont.pdf
doc/Paper/val_covar_lss_sph.pdf
doc/Paper/val_sigmas_cmb_sph.pdf
doc/api/pymaster.bins.rst
doc/api/pymaster.covariance.rst
doc/api/pymaster.field.rst
doc/api/pymaster.rst
doc/api/pymaster.utils.rst
doc/api/pymaster.workspaces.rst
doc/figs/cls_tpltz.png
doc/figs/cls_workspaces.png
doc/figs/mcms_tpltz.png
doc/figs/sample_clusteringcatalog_coupled.png
doc/figs/sample_clusteringcatalog_decoupled.png
doc/figs/sample_shearcatalog_decoupled.png
doc/figs/sample_shearcatalog_mask.png
doc/figs/sample_shearcatalog_mask_pcl.png
pymaster.egg-info/PKG-INFO
pymaster.egg-info/SOURCES.txt
pymaster.egg-info/dependency_links.txt
pymaster.egg-info/requires.txt
pymaster.egg-info/top_level.txt
