Metadata-Version: 2.1
Name: pymaster
Version: 2.6
Summary: Library for pseudo-Cl computation
Author-email: David Alonso <david.alonso@physics.ox.ac.uk>
License: Copyright (c) 2018 David Alonso (david.alonso@physics.ox.ac.uk).
Project-URL: Repository, https://github.com/LSSTDESC/NaMaster.git
Project-URL: Documentation, https://namaster.readthedocs.io/en/latest/
Project-URL: Changelog, https://github.com/LSSTDESC/NaMaster/blob/master/CHANGELOG.md
Project-URL: Issues, https://github.com/LSSTDESC/NaMaster/issues
Classifier: License :: OSI Approved :: BSD License
Classifier: Programming Language :: Python :: 3
Classifier: Operating System :: Unix
Classifier: Operating System :: MacOS
Requires-Python: >=3.10
License-File: LICENSE
Requires-Dist: healpy
Requires-Dist: ducc0
